LICENSE.md
MANIFEST.in
README.rst
pyproject.toml
setup.cfg
setup.py
django_to_rest.egg-info/PKG-INFO
django_to_rest.egg-info/SOURCES.txt
django_to_rest.egg-info/dependency_links.txt
django_to_rest.egg-info/requires.txt
django_to_rest.egg-info/top_level.txt
to_rest/__init__.py
to_rest/apps.py
to_rest/cfg.py
to_rest/constants.py
to_rest/decorators.py
to_rest/exceptions.py
to_rest/serializers.py
to_rest/utils.py
to_rest/views.py